Metadata-Version: 1.1
Name: mazepy
Version: 0.3
Summary: Setuptools setup.py for mazepy.
Home-page: https://github.com/samisalkosuo/mazepy
Author: Sami Salkosuo
Author-email: dev@rnd-dev.com
License: MIT
Platform: UNKNOWN
Classifier: Development Status :: 3 - Alpha
Classifier: Intended Audience :: Developers
Classifier: License :: OSI Approved :: MIT License
Classifier: Topic :: Software Development :: Libraries :: Python Modules
Classifier: Natural Language :: English
Classifier: Operating System :: OS Independent
Classifier: Programming Language :: Python :: 3.4
Classifier: Programming Language :: Python :: 3.5
Classifier: Programming Language :: Python :: 3 :: Only
